{"sc": "\n      \n\n\n\n\n    England 6\n  \n\n\n\n\n    France 7\n  \n\n\n\n\n    Germany 3\n  \n\n\n\n\n    Russia 1\n  \n\n\n\n\n    Turkey 17\n  \n\n\n\n\n\n\n\n\n\n\n\n\n\n\n\n\n\n\nOrders\n\n\n", "orders": {"Turkey": {"Con": {"unit_type": "A", "type": "BUILD", "result": "SUCCEEDS"}}, "Germany": {"Kie": {"unit_type": "A", "type": "BUILD", "result": "SUCCEEDS"}}}, "territories": {"Par": "Russia", "Smy": "Turkey", "Hol": "France", "Lon": "England", "Nap": "Turkey", "Gre": "Turkey", "Ven": "Turkey", "Mun": "Turkey", "War": "Turkey", "Mar": "France", "Rum": "Turkey", "Mos": "Turkey", "Tun": "France", "Bud": "Turkey", "Tri": "Turkey", "Bul": "Turkey", "Lvp": "England", "Bel": "France", "Swe": "England", "Stp": "England", "Den": "Germany", "Ber": "Germany", "Con": "Turkey", "Sev": "Turkey", "Rom": "Turkey", "Vie": "Turkey", "Edi": "England", "Por": "France", "Nwy": "England", "Ank": "Turkey", "Kie": "Germany", "Ser": "Turkey", "Spa": "France", "Bre": "France"}}