{"sc": "\n      \n\n\n\n\n    Austria 4\n  \n\n\n\n\n    England 5\n  \n\n\n\n\n    France 5\n  \n\n\n\n\n    Germany 5\n  \n\n\n\n\n    Italy 4\n  \n\n\n\n\n    Russia 5\n  \n\n\n\n\n    Turkey 4\n  \n\n\n\n\n\n\n\n\n\n\n\n\n\n\n\n\n\n\nOrders\n\n\n", "orders": {"Turkey": {"Ank": {"to": "Arm", "type": "MOVE", "result": "SUCCEEDS", "result_reason": "Attack strength is greater"}, "Bul": {"to": "Rum", "type": "MOVE", "result": "FAILS", "result_reason": "Attack strength is not greater than the defend strength"}, "Smy": {"to": "Con", "type": "MOVE", "result": "SUCCEEDS", "result_reason": "Attack strength is greater"}, "Con": {"to": "Ank", "type": "MOVE", "result": "SUCCEEDS", "result_reason": "Attack strength is greater"}}, "Italy": {"ION": {"to": "Tun", "type": "MOVE", "result": "SUCCEEDS", "result_reason": "Attack strength is greater"}, "Nap": {"to": "TYS", "type": "MOVE", "result": "SUCCEEDS", "result_reason": "Attack strength is greater"}, "Gre": {"type": "HOLD", "result": "SUCCEEDS", "result_reason": "Unchallenged"}, "Rom": {"to": "Ven", "type": "MOVE", "result": "SUCCEEDS", "result_reason": "Attack strength is greater"}}, "France": {"Bur": {"to": "Mar", "type": "MOVE", "result": "SUCCEEDS", "result_reason": "Attack strength is greater"}, "Spa": {"to": "LYO", "type": "MOVE", "result": "SUCCEEDS", "result_reason": "Attack strength is greater"}, "Bre": {"to": "MAO", "type": "MOVE", "result": "SUCCEEDS", "result_reason": "Attack strength is greater"}, "Mar": {"to": "Pie", "type": "MOVE", "result": "SUCCEEDS", "result_reason": "Attack strength is greater"}, "Por": {"to": "Spa", "type": "MOVE", "result": "SUCCEEDS", "result_reason": "Attack strength is greater"}}, "Austria": {"Tri": {"to": "Vie", "type": "MOVE", "result": "SUCCEEDS", "result_reason": "Attack strength is greater"}, "Alb": {"from": "Ser", "type": "SUPPORT", "result": "FAILS", "result_reason": "Invalid Order"}, "Ser": {"type": "HOLD", "result": "SUCCEEDS", "result_reason": "Unchallenged"}, "Bud": {"type": "HOLD", "result": "SUCCEEDS", "result_reason": "Unchallenged"}}, "Germany": {"Hol": {"type": "HOLD", "result": "SUCCEEDS", "result_reason": "Unchallenged"}, "Mun": {"type": "HOLD", "result": "SUCCEEDS", "result_reason": "Unchallenged"}, "Den": {"to": "Swe", "type": "MOVE", "result": "FAILS", "result_reason": "Attack strength is not greater than the prevent strength"}, "Ruh": {"type": "HOLD", "result": "SUCCEEDS", "result_reason": "Unchallenged"}, "Kie": {"to": "BAL", "type": "MOVE", "result": "SUCCEEDS", "result_reason": "Attack strength is greater"}}, "England": {"NWG": {"to": "BAR", "type": "MOVE", "result": "SUCCEEDS", "result_reason": "Attack strength is greater"}, "Nwy": {"to": "Stp", "type": "MOVE", "result": "FAILS", "result_reason": "Attack strength is not greater than the defend strength"}, "Lvp": {"to": "Edi", "type": "MOVE", "result": "SUCCEEDS", "result_reason": "Attack strength is greater"}, "Bel": {"to": "NTH", "type": "MOVE", "result": "SUCCEEDS", "result_reason": "Attack strength is greater"}, "Edi": {"to": "NWG", "type": "MOVE", "result": "SUCCEEDS", "result_reason": "Attack strength is greater"}}, "Russia": {"BLA": {"to": "Bul", "result_reason": "Invalid Order", "type": "SUPPORT", "result": "FAILS", "from": "Ser"}, "Stp": {"type": "HOLD", "result": "SUCCEEDS", "result_reason": "Stronger defense"}, "BOT": {"to": "Swe", "type": "MOVE", "result": "FAILS", "result_reason": "Attack strength is not greater than the prevent strength"}, "Ukr": {"from": "Rum", "type": "SUPPORT", "result": "SUCCEEDS", "result_reason": "Unchallenged"}, "Rum": {"to": "Bul", "result_reason": "Invalid Order", "type": "SUPPORT", "result": "FAILS", "from": "Ser"}}}, "territories": {"Par": "France", "Smy": "Turkey", "Hol": "Germany", "Lon": "England", "Nap": "Italy", "Gre": "Italy", "Ven": "Italy", "Mun": "Germany", "War": "Russia", "Mar": "France", "Rum": "Russia", "Mos": "Russia", "Bul": "Turkey", "Bud": "Austria", "Tri": "Austria", "Lvp": "England", "Bel": "England", "Stp": "Russia", "Den": "Germany", "Ber": "Germany", "Con": "Turkey", "Sev": "Russia", "Rom": "Italy", "Vie": "Austria", "Edi": "England", "Por": "France", "Nwy": "England", "Ank": "Turkey", "Kie": "Germany", "Ser": "Austria", "Spa": "France", "Bre": "France"}}