{"sc": "\n      \n\n\n\n\n    Austria 4\n  \n\n\n\n\n    England 4\n  \n\n\n\n\n    France 6\n  \n\n\n\n\n    Germany 5\n  \n\n\n\n\n    Italy 4\n  \n\n\n\n\n    Russia 5\n  \n\n\n\n\n    Turkey 5\n  \n\n\n\n\n\n\n\n\n\n\n\n\n\n\n\n\n\n\nResults\n\n\n", "orders": {"Turkey": {"Tri": {"to": "Ser", "type": "MOVE", "result": "SUCCEEDS", "result_reason": "Attack strength is greater"}, "Ank": {"to": "Con", "type": "MOVE", "result": "FAILS", "result_reason": "Attack strength is not greater than the prevent strength"}, "Bul": {"to": "Ser", "result_reason": "Unchallenged", "type": "SUPPORT", "result": "SUCCEEDS", "from": "Tri"}, "Smy": {"to": "Con", "type": "MOVE", "result": "FAILS", "result_reason": "Attack strength is not greater than the prevent strength"}, "Rum": {"from": "Bul", "type": "SUPPORT", "result": "SUCCEEDS", "result_reason": "Unchallenged"}}, "Italy": {"Ven": {"type": "HOLD", "result": "FAILS", "retreat": {"to": "Rom", "type": "MOVE", "result": "SUCCEEDS"}, "result_reason": "Insufficient hold strength"}, "Syr": {"to": "Gre", "type": "MOVE", "result": "SUCCEEDS", "result_reason": "Attack strength is greater"}, "EAS": {"to": "Gre", "result_reason": "Unchallenged", "type": "CONVOY", "result": "SUCCEEDS", "from": "Syr"}, "ION": {"to": "Gre", "result_reason": "Unchallenged", "type": "CONVOY", "result": "SUCCEEDS", "from": "Syr"}}, "France": {"Bel": {"to": "NTH", "result_reason": "Neither displaced nor disrupted", "type": "SUPPORT", "result": "SUCCEEDS", "from": "ENG"}, "ENG": {"to": "NTH", "type": "MOVE", "result": "SUCCEEDS", "result_reason": "Attack strength is greater"}, "Tus": {"to": "Ven", "result_reason": "Unchallenged", "type": "SUPPORT", "result": "SUCCEEDS", "from": "Pie"}, "Pie": {"to": "Ven", "type": "MOVE", "result": "SUCCEEDS", "result_reason": "Attack strength is greater"}, "WES": {"to": "Tun", "type": "MOVE", "result": "SUCCEEDS", "result_reason": "Attack strength is greater"}, "TYS": {"to": "Tun", "result_reason": "Unchallenged", "type": "SUPPORT", "result": "SUCCEEDS", "from": "WES"}}, "Austria": {"Ser": {"from": "Ven", "result_reason": "Invalid Order", "to": "Tri", "result": "FAILS", "type": "SUPPORT", "retreat": {"to": "Alb", "type": "MOVE", "result": "SUCCEEDS"}}, "AEG": {"to": "Smy", "result_reason": "Invalid Order", "type": "SUPPORT", "result": "FAILS", "from": "EAS"}, "Vie": {"to": "Tri", "result_reason": "Invalid Order", "type": "SUPPORT", "result": "FAILS", "from": "Ven"}}, "Germany": {"Boh": {"from": "Vie", "type": "SUPPORT", "result": "SUCCEEDS", "result_reason": "Unchallenged"}, "Hol": {"from": "Bel", "type": "SUPPORT", "result": "SUCCEEDS", "result_reason": "Unchallenged"}, "Swe": {"to": "Nwy", "type": "MOVE", "result": "FAILS", "result_reason": "Attack strength is not greater than the defend strength"}, "BAL": {"to": "BOT", "type": "MOVE", "result": "SUCCEEDS", "result_reason": "Attack strength is greater"}, "Den": {"type": "HOLD", "result": "SUCCEEDS", "result_reason": "Unchallenged"}}, "England": {"NTH": {"from": "Lon", "result_reason": "Contradiction!", "to": "Bel", "result": "FAILS", "type": "CONVOY", "retreat": {"to": "Edi", "type": "MOVE", "result": "SUCCEEDS"}}, "Wal": {"type": "HOLD", "result": "SUCCEEDS", "result_reason": "Unchallenged"}, "Lon": {"to": "Bel", "type": "MOVE", "result": "FAILS", "result_reason": "Invalid move path"}, "Nwy": {"from": "NTH", "type": "SUPPORT", "result": "FAILS", "result_reason": "Disrupted"}}, "Russia": {"Lvn": {"to_coast": "sc", "from": "Stp", "type": "SUPPORT", "result": "SUCCEEDS", "result_reason": "Unchallenged"}, "Gal": {"to": "Vie", "type": "MOVE", "result": "FAILS", "result_reason": "Attack strength is not greater than the defend strength"}, "Stp": {"from": "Nwy", "type": "SUPPORT", "result": "FAILS", "result_reason": "Invalid Order"}, "War": {"to": "Gal", "type": "MOVE", "result": "FAILS", "result_reason": "Attack strength is not greater than the defend strength"}, "Bud": {"to": "Vie", "result_reason": "Unchallenged", "type": "SUPPORT", "result": "SUCCEEDS", "from": "Gal"}}}, "territories": {"Par": "France", "Smy": "Turkey", "Hol": "Germany", "Lon": "England", "Nap": "Italy", "Gre": "Austria", "Ven": "Italy", "Mun": "Germany", "War": "Russia", "Lvp": "England", "Mar": "France", "Rum": "Turkey", "Mos": "Russia", "Bul": "Austria", "Bud": "Austria", "Tri": "Austria", "Tun": "Italy", "Bel": "France", "Stp": "Russia", "Den": "Germany", "Ber": "Germany", "Con": "Turkey", "Sev": "Russia", "Rom": "Italy", "Vie": "Russia", "Edi": "England", "Por": "France", "Nwy": "England", "Ank": "Turkey", "Kie": "Germany", "Ser": "Turkey", "Spa": "France", "Bre": "France"}}