{"sc": "\n      \n\n\n\n\n    Austria 3\n  \n\n\n\n\n    England 4\n  \n\n\n\n\n    France 4\n  \n\n\n\n\n    Germany 5\n  \n\n\n\n\n    Italy 5\n  \n\n\n\n\n    Russia 7\n  \n\n\n\n\n    Turkey 4\n  \n\n\n\n\n\n\n\n\n\n\n\n\n\n\n\n\n\n\nOrders\n\n\n", "orders": {"Turkey": {"Bul": {"to": "Ser", "type": "MOVE", "result": "SUCCEEDS", "result_reason": "Attack strength is greater"}, "AEG": {"to": "ION", "result_reason": "Unchallenged", "type": "SUPPORT", "result": "SUCCEEDS", "from": "Gre"}, "Smy": {"to": "EAS", "type": "MOVE", "result": "SUCCEEDS", "result_reason": "Attack strength is greater"}, "Ank": {"to": "Bul", "type": "MOVE", "result": "SUCCEEDS", "result_reason": "Attack strength is greater"}}, "Italy": {"Ven": {"from": "Tri", "type": "SUPPORT", "result": "SUCCEEDS", "result_reason": "Unchallenged"}, "Tri": {"to": "Bud", "result_reason": "Unchallenged", "type": "SUPPORT", "result": "SUCCEEDS", "from": "Vie"}, "Nap": {"to": "ION", "type": "MOVE", "result": "FAILS", "result_reason": "Attack strength is not greater than the prevent strength"}, "Rom": {"to": "TYS", "type": "MOVE", "result": "SUCCEEDS", "result_reason": "Attack strength is greater"}, "Tun": {"to": "WES", "type": "MOVE", "result": "SUCCEEDS", "result_reason": "Attack strength is greater"}}, "France": {"Bur": {"to": "Mar", "type": "MOVE", "result": "SUCCEEDS", "result_reason": "Attack strength is greater"}, "Par": {"to": "Bur", "type": "MOVE", "result": "SUCCEEDS", "result_reason": "Attack strength is greater"}, "Por": {"to": "MAO", "type": "MOVE", "result": "SUCCEEDS", "result_reason": "Attack strength is greater"}, "Bre": {"to": "Par", "type": "MOVE", "result": "SUCCEEDS", "result_reason": "Attack strength is greater"}}, "Austria": {"Gre": {"to": "ION", "type": "MOVE", "result": "SUCCEEDS", "result_reason": "Attack strength is greater"}, "Ser": {"to": "Bud", "type": "MOVE", "result": "SUCCEEDS", "result_reason": "Attack strength is greater"}, "Vie": {"to": "Bud", "result_reason": "Neither displaced nor disrupted", "type": "SUPPORT", "result": "SUCCEEDS", "from": "Ser"}}, "Germany": {"Ber": {"to": "Kie", "type": "MOVE", "result": "SUCCEEDS", "result_reason": "Attack strength is greater"}, "Hol": {"to": "HEL", "type": "MOVE", "result": "SUCCEEDS", "result_reason": "Attack strength is greater"}, "Mun": {"to": "Tyr", "type": "MOVE", "result": "SUCCEEDS", "result_reason": "Attack strength is greater"}, "Bel": {"to": "Ruh", "type": "MOVE", "result": "SUCCEEDS", "result_reason": "Attack strength is greater"}, "Kie": {"to": "BAL", "type": "MOVE", "result": "SUCCEEDS", "result_reason": "Attack strength is greater"}}, "England": {"Pic": {"to": "Bel", "type": "MOVE", "result": "SUCCEEDS", "result_reason": "Attack strength is greater"}, "Nwy": {"to": "Swe", "type": "MOVE", "result": "FAILS", "retreat": {"to": "SKA", "type": "MOVE", "result": "SUCCEEDS"}, "result_reason": "Attack strength is not greater than the defend strength"}, "Lvp": {"to": "NAO", "type": "MOVE", "result": "SUCCEEDS", "result_reason": "Attack strength is greater"}, "ENG": {"to": "NTH", "type": "MOVE", "result": "SUCCEEDS", "result_reason": "Attack strength is greater"}}, "Russia": {"Sev": {"to": "Ukr", "type": "MOVE", "result": "SUCCEEDS", "result_reason": "Attack strength is greater"}, "Rum": {"to": "Ser", "result_reason": "Unchallenged", "type": "SUPPORT", "result": "SUCCEEDS", "from": "Bul"}, "Mos": {"to": "Stp", "type": "MOVE", "result": "SUCCEEDS", "result_reason": "Attack strength is greater"}, "Swe": {"to": "Nwy", "result_reason": "Neither displaced nor disrupted", "type": "SUPPORT", "result": "SUCCEEDS", "from": "Stp"}, "Stp": {"to": "Nwy", "type": "MOVE", "result": "SUCCEEDS", "result_reason": "Attack strength is greater"}, "BLA": {"to": "Bul", "result_reason": "Unchallenged", "type": "CONVOY", "result": "SUCCEEDS", "from": "Ank"}, "Bud": {"to": "Vie", "type": "MOVE", "result": "FAILS", "retreat": {"to": "Gal", "type": "MOVE", "result": "SUCCEEDS"}, "result_reason": "Attack strength is not greater than the defend strength"}}}, "territories": {"Par": "France", "Smy": "Turkey", "Hol": "Germany", "Lon": "England", "Nap": "Italy", "Gre": "Austria", "Ven": "Italy", "Mun": "Germany", "War": "Russia", "Mar": "France", "Rum": "Russia", "Mos": "Russia", "Tun": "Italy", "Bul": "Turkey", "Bud": "Russia", "Tri": "Italy", "Lvp": "England", "Bel": "Germany", "Swe": "Russia", "Stp": "Russia", "Ber": "Germany", "Con": "Turkey", "Sev": "Russia", "Rom": "Italy", "Vie": "Austria", "Edi": "England", "Por": "France", "Nwy": "England", "Ank": "Turkey", "Kie": "Germany", "Ser": "Austria", "Bre": "France"}}